experiment_develop/__init__.py
experiment_develop/main.py
experiment_develop-0.1.0.dist-info/WHEEL
experiment_develop-0.1.0.dist-info/METADATA
experiment_develop-0.1.0.dist-info/RECORD
