Metadata-Version: 2.1
Name: experiment-develop
Version: 0.1.0
Summary: All for me
Author: Ochi Yuma
Author-email: ochiyuma.ochi@gmail.com
Requires-Python: >=3.9,<4.0
Classifier: Programming Language :: Python :: 3
Classifier: Programming Language :: Python :: 3.10
Classifier: Programming Language :: Python :: 3.9
Requires-Dist: numpy (>=1.22.0,<2.0.0)
